djangocraft/__init__.py
djangocraft/__main__.py
djangocraft-1.0.1.dist-info/LICENSE
djangocraft-1.0.1.dist-info/METADATA
djangocraft-1.0.1.dist-info/WHEEL
djangocraft-1.0.1.dist-info/entry_points.txt
djangocraft-1.0.1.dist-info/top_level.txt
djangocraft-1.0.1.dist-info/RECORD
