Metadata-Version: 2.1
Name: djangocraft
Version: 1.0.1
Summary: A easy way to setup your projects with a easy pre-built authentication
Author-email: Yash <yashraj504300@gmail.com>
License: MIT License
Project-URL: Homepage, https://github.com/YashRaj1506/djangocraft
Classifier: License :: OSI Approved :: MIT License
Classifier: Programming Language :: Python
Classifier: Programming Language :: Python :: 3
Requires-Python: >3.6
License-File: LICENSE
Requires-Dist: typer[all] >=0.9.0
